{"name":"Bharash Drakaron","image":"https://cdn.discordapp.com/attachments/747181944478892112/750752397738901584/unknown.png","HP":"12","base_HP":"12","MP":"empty","levels":"1","age":"empty","job":"guerrier","race":"sangdragon","money":"10 PO","alignment":"empty","proficiency":"empty","initiative":"0","attack":"empty","defense":"14","traits":["Acrobaties +0","Arcanes +2","Athlétisme +1","Discrétion +0","Dressage +0","Escamotage +0","Histoire +4","Intimidation +3","Investigation +2","Médecine -2","Nature +2","Perception -2","Perspicacité -2","Persuasion +1","Religion +2","Représentation +1","Survie +0","Tromperie +1"],"stats":[{"Force":"13"},{"Dexterité":"11"},{"Constitution":"15"},{"Intelligence":"15"},{"Sagesse":"7"},{"Charisme":"12"}],"inventory":[{"outil de depeceur":1},{"pelle et marmitte":1},{"pack d'explorateur souterraine":1}],"skills":"empty","spells":"empty"}